{
  "contacts": [
    {
      "id": "0034600000y8VkAAAU",
      "email": "president@whitehouse.gov",
      "accountid": "0014600000V4rm4AAB",
      "firstname": "Barack5",
      "lastname": "Obama"
    }
  ],

  "countries": [
    {
      "id": "IT",
      "name": "Italy",
      "capitalCity": "Rome",
      "phoneCode": "39",
      "continentCode": "EU",
      "currencyCode": "EUR",
      "countryFlag": "http://www.oorsprong.org/WebSamples.CountryInfo/Images/Italy.jpg",
      "languages": [
        {
          "languageCode": "ita",
          "languageName": "Italian"
        }
      ]
    }
  ],

  "things": [
    {
      "id": 100,
      "name": "foo",
      "title": "title",
      "code": "code",
      "price": 10.5,
      "active": true,
      "created": "1995-12-17T03:24:00"
    }
  ],

  "sf-accounts": [
    {
      "id": "0014600000WNlJvAAL",
      "accountNumber": "600000001120",
      "accountSource": null,
      "annualRevenue": 0,
      "name": "Cheese's Sample Project",
      "type": null
    },
    {
      "id": "00146000012BteOAAS",
      "accountNumber": "cs-no-src",
      "accountSource": "Yori",
      "annualRevenue": 100,
      "name": "cs-no-src-account",
      "type": null
    },
    {
      "id": "00146000012Bq3nAAC",
      "accountNumber": "cs-1057-2c",
      "accountSource": "Yori",
      "annualRevenue": 200,
      "name": "cs-1057-2c-account",
      "type": null
    },
    {
      "id": "00146000012BqxkAAC",
      "accountNumber": "ds-shared-ftp-src",
      "accountSource": "Yori",
      "annualRevenue": 123,
      "name": "ds-shared-ftp-src-account",
      "type": null
    },
    {
      "id": "00146000012BrZgAAK",
      "accountNumber": "cs-shared-ftp-src",
      "accountSource": "Yori",
      "annualRevenue": 321,
      "name": "cs-shared-ftp-src-account",
      "type": null
    },
    {
      "id": "00146000012Bq3iAAC",
      "accountNumber": "cs-1057-2c",
      "accountSource": "Yori",
      "annualRevenue": 200,
      "name": "cs-1057-2c-account",
      "type": null
    },
    {
      "id": "0014600000V4rm4AAB",
      "accountNumber": "CC978213",
      "accountSource": null,
      "annualRevenue": 30000000,
      "name": "GenePoint",
      "numberOfEmployees": 265,
      "type": "Customer - Channel"
    },
    {
      "id": "0014600000V4rm2AAB",
      "accountNumber": "CD355119-A",
      "accountSource": null,
      "annualRevenue": 0,
      "name": "United Oil & Gas, UK",
      "numberOfEmployees": 24000,
      "type": "Customer - Direct"
    },
    {
      "id": "0014600000V4rm3AAB",
      "accountNumber": "CD355120-B",
      "accountSource": null,
      "annualRevenue": 0,
      "name": "United Oil & Gas, Singapore",
      "numberOfEmployees": 3000,
      "type": "Customer - Direct"
    },
    {
      "id": "0014600000V4rluAAB",
      "accountNumber": "CD451796",
      "accountSource": null,
      "annualRevenue": 139000000,
      "name": "Edge Communications",
      "numberOfEmployees": 1000,
      "type": "Customer - Direct"
    }
  ]
}